django_tenants/__init__.py
django_tenants/admin.py
django_tenants/apps.py
django_tenants/cache.py
django_tenants/clone.py
django_tenants/log.py
django_tenants/models.py
django_tenants/routers.py
django_tenants/signals.py
django_tenants/urlresolvers.py
django_tenants/utils.py
django_tenants/files/__init__.py
django_tenants/files/storage.py
django_tenants/files/storages.py
django_tenants/management/__init__.py
django_tenants/management/commands/__init__.py
django_tenants/management/commands/all_tenants_command.py
django_tenants/management/commands/clone_tenant.py
django_tenants/management/commands/collectstatic_schemas.py
django_tenants/management/commands/create_missing_schemas.py
django_tenants/management/commands/create_tenant.py
django_tenants/management/commands/create_tenant_superuser.py
django_tenants/management/commands/delete_tenant.py
django_tenants/management/commands/migrate.py
django_tenants/management/commands/migrate_schemas.py
django_tenants/management/commands/rename_schema.py
django_tenants/management/commands/tenant_command.py
django_tenants/middleware/__init__.py
django_tenants/middleware/default.py
django_tenants/middleware/main.py
django_tenants/middleware/subfolder.py
django_tenants/middleware/suspicious.py
django_tenants/migration_executors/__init__.py
django_tenants/migration_executors/base.py
django_tenants/migration_executors/multiproc.py
django_tenants/migration_executors/standard.py
django_tenants/postgresql_backend/__init__.py
django_tenants/postgresql_backend/base.py
django_tenants/postgresql_backend/introspection.py
django_tenants/staticfiles/__init__.py
django_tenants/staticfiles/finders.py
django_tenants/staticfiles/storage.py
django_tenants/template/__init__.py
django_tenants/template/loaders/__init__.py
django_tenants/template/loaders/cached.py
django_tenants/template/loaders/filesystem.py
django_tenants/templates/admin/app_list.html
django_tenants/templates/admin/index.html
j2_django_tenants-3.6.1.dist-info/LICENSE
j2_django_tenants-3.6.1.dist-info/METADATA
j2_django_tenants-3.6.1.dist-info/WHEEL
j2_django_tenants-3.6.1.dist-info/top_level.txt
j2_django_tenants-3.6.1.dist-info/RECORD
